setup.py
split_block/__init__.py
split_block/apart.py
split_block/group.py
split_block/group_chapped.py
split_block/group_ext.py
split_block/item.py
split_block.egg-info/PKG-INFO
split_block.egg-info/SOURCES.txt
split_block.egg-info/dependency_links.txt
split_block.egg-info/not-zip-safe
split_block.egg-info/pbr.json
split_block.egg-info/requires.txt
split_block.egg-info/top_level.txt