Metadata-Version: 1.1
Name: split-block
Version: 0.0.2
Summary: split_block
Home-page: http://github.com/mvj3/split_block/
Author: David Chen
Author-email: mvjome@gmail.com
License: MIT
Platform: any
Classifier: Intended Audience :: Developers
Classifier: Operating System :: OS Independent
Classifier: Programming Language :: Python
Classifier: Topic :: Software Development :: Libraries :: Python Modules
